COPYING
MANIFEST.in
Makefile
NEWS
README
TODO
cupsconnection.c
cupsconnection.h
cupsipp.c
cupsipp.h
cupsmodule.c
cupsmodule.h
cupsppd.c
cupsppd.h
postscriptdriver.prov
psdriver.attr
setup.py
test.py
examples/cupstree.py
pycups.egg-info/PKG-INFO
pycups.egg-info/SOURCES.txt
pycups.egg-info/dependency_links.txt
pycups.egg-info/requires.txt
pycups.egg-info/top_level.txt