Metadata-Version: 2.1
Name: pycups
Version: 2.0.2a0
Summary: Python bindings for libcups
Home-page: https://github.com/OpenPrinting/pycups
Download-URL: https://github.com/OpenPrinting/pycups/releases
Maintainer: Zdenek Dohnal
Maintainer-email: zdohnal@redhat.com
License: GPLv2+
Classifier: Intended Audience :: Developers
Classifier: Topic :: Software Development :: Libraries :: Python Modules
Classifier: License :: OSI Approved :: GNU General Public License (GPL)
Classifier: Development Status :: 5 - Production/Stable
Classifier: Operating System :: Unix
Classifier: Programming Language :: C
Classifier: Programming Language :: Python
Classifier: Programming Language :: Python :: 3
License-File: COPYING
Requires-Dist: gcc
Requires-Dist: python3-devel
